{
  "blocks": [
    {
      "ep": 16187680,
      "len": 33,
      "pred": [],
      "succ": [
        {
          "cond": true,
          "ep": 16187869
        },
        {
          "cond": false,
          "ep": 16187713
        }
      ]
    },
    {
      "ep": 16187869,
      "len": 9,
      "pred": [
        16187680
      ],
      "succ": [
        {
          "cond": true,
          "ep": 16188290
        }
      ]
    },
    {
      "ep": 16188290,
      "len": 76,
      "pred": [
        16187869,
        16187878,
        16187887,
        16187896,
        16187905,
        16187914,
        16187923,
        16187932,
        16187963,
        16187972,
        16187954,
        16188003,
        16188012,
        16187994,
        16188043,
        16188052,
        16188034,
        16188083,
        16188092,
        16188074,
        16188123,
        16188132,
        16188114,
        16188141,
        16188150,
        16188159,
        16188168,
        16188177
      ],
      "succ": [
        {
          "cond": true,
          "ep": 16188186
        }
      ]
    },
    {
      "ep": 16188186,
      "len": 8,
      "pred": [
        16188290,
        16187865
      ],
      "succ": []
    },
    {
      "ep": 16187713,
      "len": 8,
      "pred": [
        16187680
      ],
      "succ": [
        {
          "cond": true,
          "ep": 16187878
        },
        {
          "cond": false,
          "ep": 16187721
        }
      ]
    },
    {
      "ep": 16187878,
      "len": 9,
      "pred": [
        16187713
      ],
      "succ": [
        {
          "cond": true,
          "ep": 16188290
        }
      ]
    },
    {
      "ep": 16187721,
      "len": 8,
      "pred": [
        16187713
      ],
      "succ": [
        {
          "cond": true,
          "ep": 16187887
        },
        {
          "cond": false,
          "ep": 16187729
        }
      ]
    },
    {
      "ep": 16187887,
      "len": 9,
      "pred": [
        16187721
      ],
      "succ": [
        {
          "cond": true,
          "ep": 16188290
        }
      ]
    },
    {
      "ep": 16187729,
      "len": 8,
      "pred": [
        16187721
      ],
      "succ": [
        {
          "cond": true,
          "ep": 16187896
        },
        {
          "cond": false,
          "ep": 16187737
        }
      ]
    },
    {
      "ep": 16187896,
      "len": 9,
      "pred": [
        16187729
      ],
      "succ": [
        {
          "cond": true,
          "ep": 16188290
        }
      ]
    },
    {
      "ep": 16187737,
      "len": 8,
      "pred": [
        16187729
      ],
      "succ": [
        {
          "cond": true,
          "ep": 16187905
        },
        {
          "cond": false,
          "ep": 16187745
        }
      ]
    },
    {
      "ep": 16187905,
      "len": 9,
      "pred": [
        16187737
      ],
      "succ": [
        {
          "cond": true,
          "ep": 16188290
        }
      ]
    },
    {
      "ep": 16187745,
      "len": 8,
      "pred": [
        16187737
      ],
      "succ": [
        {
          "cond": true,
          "ep": 16187914
        },
        {
          "cond": false,
          "ep": 16187753
        }
      ]
    },
    {
      "ep": 16187914,
      "len": 9,
      "pred": [
        16187745
      ],
      "succ": [
        {
          "cond": true,
          "ep": 16188290
        }
      ]
    },
    {
      "ep": 16187753,
      "len": 8,
      "pred": [
        16187745
      ],
      "succ": [
        {
          "cond": true,
          "ep": 16187923
        },
        {
          "cond": false,
          "ep": 16187761
        }
      ]
    },
    {
      "ep": 16187923,
      "len": 9,
      "pred": [
        16187753
      ],
      "succ": [
        {
          "cond": true,
          "ep": 16188290
        }
      ]
    },
    {
      "ep": 16187761,
      "len": 8,
      "pred": [
        16187753
      ],
      "succ": [
        {
          "cond": true,
          "ep": 16187932
        },
        {
          "cond": false,
          "ep": 16187769
        }
      ]
    },
    {
      "ep": 16187932,
      "len": 9,
      "pred": [
        16187761
      ],
      "succ": [
        {
          "cond": true,
          "ep": 16188290
        }
      ]
    },
    {
      "ep": 16187769,
      "len": 8,
      "pred": [
        16187761
      ],
      "succ": [
        {
          "cond": true,
          "ep": 16187941
        },
        {
          "cond": false,
          "ep": 16187777
        }
      ]
    },
    {
      "ep": 16187941,
      "len": 9,
      "pred": [
        16187769,
        16187777
      ],
      "succ": [
        {
          "cond": true,
          "ep": 16187963
        },
        {
          "cond": false,
          "ep": 16187950
        }
      ]
    },
    {
      "ep": 16187963,
      "len": 9,
      "pred": [
        16187941
      ],
      "succ": [
        {
          "cond": true,
          "ep": 16188290
        }
      ]
    },
    {
      "ep": 16187950,
      "len": 4,
      "pred": [
        16187941
      ],
      "succ": [
        {
          "cond": true,
          "ep": 16187972
        },
        {
          "cond": false,
          "ep": 16187954
        }
      ]
    },
    {
      "ep": 16187972,
      "len": 9,
      "pred": [
        16187950
      ],
      "succ": [
        {
          "cond": true,
          "ep": 16188290
        }
      ]
    },
    {
      "ep": 16187954,
      "len": 9,
      "pred": [
        16187950
      ],
      "succ": [
        {
          "cond": true,
          "ep": 16188290
        }
      ]
    },
    {
      "ep": 16187777,
      "len": 8,
      "pred": [
        16187769
      ],
      "succ": [
        {
          "cond": true,
          "ep": 16187941
        },
        {
          "cond": false,
          "ep": 16187785
        }
      ]
    },
    {
      "ep": 16187785,
      "len": 8,
      "pred": [
        16187777
      ],
      "succ": [
        {
          "cond": true,
          "ep": 16187981
        },
        {
          "cond": false,
          "ep": 16187793
        }
      ]
    },
    {
      "ep": 16187981,
      "len": 9,
      "pred": [
        16187785
      ],
      "succ": [
        {
          "cond": true,
          "ep": 16188003
        },
        {
          "cond": false,
          "ep": 16187990
        }
      ]
    },
    {
      "ep": 16188003,
      "len": 9,
      "pred": [
        16187981
      ],
      "succ": [
        {
          "cond": true,
          "ep": 16188290
        }
      ]
    },
    {
      "ep": 16187990,
      "len": 4,
      "pred": [
        16187981
      ],
      "succ": [
        {
          "cond": true,
          "ep": 16188012
        },
        {
          "cond": false,
          "ep": 16187994
        }
      ]
    },
    {
      "ep": 16188012,
      "len": 9,
      "pred": [
        16187990
      ],
      "succ": [
        {
          "cond": true,
          "ep": 16188290
        }
      ]
    },
    {
      "ep": 16187994,
      "len": 9,
      "pred": [
        16187990
      ],
      "succ": [
        {
          "cond": true,
          "ep": 16188290
        }
      ]
    },
    {
      "ep": 16187793,
      "len": 8,
      "pred": [
        16187785
      ],
      "succ": [
        {
          "cond": true,
          "ep": 16188021
        },
        {
          "cond": false,
          "ep": 16187801
        }
      ]
    },
    {
      "ep": 16188021,
      "len": 9,
      "pred": [
        16187793
      ],
      "succ": [
        {
          "cond": true,
          "ep": 16188043
        },
        {
          "cond": false,
          "ep": 16188030
        }
      ]
    },
    {
      "ep": 16188043,
      "len": 9,
      "pred": [
        16188021
      ],
      "succ": [
        {
          "cond": true,
          "ep": 16188290
        }
      ]
    },
    {
      "ep": 16188030,
      "len": 4,
      "pred": [
        16188021
      ],
      "succ": [
        {
          "cond": true,
          "ep": 16188052
        },
        {
          "cond": false,
          "ep": 16188034
        }
      ]
    },
    {
      "ep": 16188052,
      "len": 9,
      "pred": [
        16188030
      ],
      "succ": [
        {
          "cond": true,
          "ep": 16188290
        }
      ]
    },
    {
      "ep": 16188034,
      "len": 9,
      "pred": [
        16188030
      ],
      "succ": [
        {
          "cond": true,
          "ep": 16188290
        }
      ]
    },
    {
      "ep": 16187801,
      "len": 8,
      "pred": [
        16187793
      ],
      "succ": [
        {
          "cond": true,
          "ep": 16188061
        },
        {
          "cond": false,
          "ep": 16187809
        }
      ]
    },
    {
      "ep": 16188061,
      "len": 9,
      "pred": [
        16187801
      ],
      "succ": [
        {
          "cond": true,
          "ep": 16188083
        },
        {
          "cond": false,
          "ep": 16188070
        }
      ]
    },
    {
      "ep": 16188083,
      "len": 9,
      "pred": [
        16188061
      ],
      "succ": [
        {
          "cond": true,
          "ep": 16188290
        }
      ]
    },
    {
      "ep": 16188070,
      "len": 4,
      "pred": [
        16188061
      ],
      "succ": [
        {
          "cond": true,
          "ep": 16188092
        },
        {
          "cond": false,
          "ep": 16188074
        }
      ]
    },
    {
      "ep": 16188092,
      "len": 9,
      "pred": [
        16188070
      ],
      "succ": [
        {
          "cond": true,
          "ep": 16188290
        }
      ]
    },
    {
      "ep": 16188074,
      "len": 9,
      "pred": [
        16188070
      ],
      "succ": [
        {
          "cond": true,
          "ep": 16188290
        }
      ]
    },
    {
      "ep": 16187809,
      "len": 8,
      "pred": [
        16187801
      ],
      "succ": [
        {
          "cond": true,
          "ep": 16188101
        },
        {
          "cond": false,
          "ep": 16187817
        }
      ]
    },
    {
      "ep": 16188101,
      "len": 9,
      "pred": [
        16187809
      ],
      "succ": [
        {
          "cond": true,
          "ep": 16188123
        },
        {
          "cond": false,
          "ep": 16188110
        }
      ]
    },
    {
      "ep": 16188123,
      "len": 9,
      "pred": [
        16188101
      ],
      "succ": [
        {
          "cond": true,
          "ep": 16188290
        }
      ]
    },
    {
      "ep": 16188110,
      "len": 4,
      "pred": [
        16188101
      ],
      "succ": [
        {
          "cond": true,
          "ep": 16188132
        },
        {
          "cond": false,
          "ep": 16188114
        }
      ]
    },
    {
      "ep": 16188132,
      "len": 9,
      "pred": [
        16188110
      ],
      "succ": [
        {
          "cond": true,
          "ep": 16188290
        }
      ]
    },
    {
      "ep": 16188114,
      "len": 9,
      "pred": [
        16188110
      ],
      "succ": [
        {
          "cond": true,
          "ep": 16188290
        }
      ]
    },
    {
      "ep": 16187817,
      "len": 8,
      "pred": [
        16187809
      ],
      "succ": [
        {
          "cond": true,
          "ep": 16188141
        },
        {
          "cond": false,
          "ep": 16187825
        }
      ]
    },
    {
      "ep": 16188141,
      "len": 9,
      "pred": [
        16187817,
        16187825
      ],
      "succ": [
        {
          "cond": true,
          "ep": 16188290
        }
      ]
    },
    {
      "ep": 16187825,
      "len": 8,
      "pred": [
        16187817
      ],
      "succ": [
        {
          "cond": true,
          "ep": 16188141
        },
        {
          "cond": false,
          "ep": 16187833
        }
      ]
    },
    {
      "ep": 16187833,
      "len": 8,
      "pred": [
        16187825
      ],
      "succ": [
        {
          "cond": true,
          "ep": 16188150
        },
        {
          "cond": false,
          "ep": 16187841
        }
      ]
    },
    {
      "ep": 16188150,
      "len": 9,
      "pred": [
        16187833
      ],
      "succ": [
        {
          "cond": true,
          "ep": 16188290
        }
      ]
    },
    {
      "ep": 16187841,
      "len": 8,
      "pred": [
        16187833
      ],
      "succ": [
        {
          "cond": true,
          "ep": 16188159
        },
        {
          "cond": false,
          "ep": 16187849
        }
      ]
    },
    {
      "ep": 16188159,
      "len": 9,
      "pred": [
        16187841
      ],
      "succ": [
        {
          "cond": true,
          "ep": 16188290
        }
      ]
    },
    {
      "ep": 16187849,
      "len": 8,
      "pred": [
        16187841
      ],
      "succ": [
        {
          "cond": true,
          "ep": 16188168
        },
        {
          "cond": false,
          "ep": 16187857
        }
      ]
    },
    {
      "ep": 16188168,
      "len": 9,
      "pred": [
        16187849
      ],
      "succ": [
        {
          "cond": true,
          "ep": 16188290
        }
      ]
    },
    {
      "ep": 16187857,
      "len": 8,
      "pred": [
        16187849
      ],
      "succ": [
        {
          "cond": true,
          "ep": 16188177
        },
        {
          "cond": false,
          "ep": 16187865
        }
      ]
    },
    {
      "ep": 16188177,
      "len": 9,
      "pred": [
        16187857
      ],
      "succ": [
        {
          "cond": true,
          "ep": 16188290
        }
      ]
    },
    {
      "ep": 16187865,
      "len": 4,
      "pred": [
        16187857
      ],
      "succ": [
        {
          "cond": true,
          "ep": 16188186
        }
      ]
    }
  ],
  "callees": [
    {
      "fun": 15852881,
      "loc": 16187683
    },
    {
      "fun": 15968856,
      "loc": 16187689
    },
    {
      "fun": 15963858,
      "loc": 16187695
    },
    {
      "fun": 16188194,
      "loc": 16187699
    },
    {
      "fun": 16258140,
      "loc": 16188186
    },
    {
      "fun": 16188366,
      "loc": 16188298
    },
    {
      "fun": 16188398,
      "loc": 16188310
    },
    {
      "fun": 16188458,
      "loc": 16188322
    },
    {
      "fun": 16188412,
      "loc": 16188334
    },
    {
      "fun": 16188444,
      "loc": 16188346
    },
    {
      "fun": 16188472,
      "loc": 16188358
    }
  ],
  "callers": [
    {
      "fun": 15797608,
      "loc": 15798641
    },
    {
      "fun": 16187485,
      "loc": 16187489
    }
  ],
  "start": 16187680,
  "state": {
    "clobbers": [
      {
        "ep": 16187689,
        "pc": 5,
        "value": {
          "address": 4201616,
          "type": "Mem"
        }
      },
      {
        "ep": 16187689,
        "pc": 5,
        "value": {
          "reg": 240,
          "size": 1,
          "type": "Reg"
        }
      },
      {
        "ep": 16187689,
        "pc": 5,
        "value": {
          "address": 2097152,
          "type": "Mem"
        }
      },
      {
        "ep": 16187689,
        "pc": 5,
        "value": {
          "address": 2097153,
          "type": "Mem"
        }
      },
      {
        "ep": 16187689,
        "pc": 5,
        "value": {
          "address": 4201615,
          "type": "Mem"
        }
      },
      {
        "ep": 16187695,
        "pc": 7,
        "value": {
          "address": 4201632,
          "type": "Mem"
        }
      },
      {
        "ep": 16187695,
        "pc": 7,
        "value": {
          "address": 4201643,
          "type": "Mem"
        }
      },
      {
        "ep": 16187695,
        "pc": 7,
        "value": {
          "address": 4201633,
          "type": "Mem"
        }
      },
      {
        "ep": 16187695,
        "pc": 7,
        "value": {
          "address": 4201631,
          "type": "Mem"
        }
      },
      {
        "ep": 16187695,
        "pc": 7,
        "value": {
          "address": 4201653,
          "type": "Mem"
        }
      },
      {
        "ep": 16187695,
        "pc": 7,
        "value": {
          "reg": 252,
          "size": 2,
          "type": "Reg"
        }
      },
      {
        "ep": 16187695,
        "pc": 7,
        "value": {
          "address": 4201630,
          "type": "Mem"
        }
      },
      {
        "ep": 16187695,
        "pc": 7,
        "value": {
          "address": 4201644,
          "type": "Mem"
        }
      },
      {
        "ep": 16187695,
        "pc": 7,
        "value": {
          "reg": 224,
          "size": 1,
          "type": "Reg"
        }
      },
      {
        "ep": 16187695,
        "pc": 7,
        "value": {
          "address": 65536,
          "type": "Mem"
        }
      },
      {
        "ep": 16187695,
        "pc": 7,
        "value": {
          "address": 65537,
          "type": "Mem"
        }
      },
      {
        "ep": 16188186,
        "pc": 51,
        "value": {
          "address": 4205138,
          "type": "Mem"
        }
      }
    ],
    "fun_stack": [],
    "input": [
      {
        "address": 18,
        "type": "Mem"
      },
      {
        "address": 4201630,
        "type": "Mem"
      },
      {
        "address": 4201631,
        "type": "Mem"
      },
      {
        "address": 4201632,
        "type": "Mem"
      },
      {
        "address": 4201633,
        "type": "Mem"
      },
      {
        "address": 4201643,
        "type": "Mem"
      },
      {
        "address": 4201684,
        "type": "Mem"
      },
      {
        "address": 4205138,
        "type": "Mem"
      },
      {
        "address": 16772665,
        "type": "Mem"
      },
      {
        "reg": 228,
        "size": 0,
        "type": "Reg"
      },
      {
        "reg": 232,
        "size": 1,
        "type": "Reg"
      },
      {
        "reg": 252,
        "size": 2,
        "type": "Reg"
      }
    ],
    "output": [],
    "pc": 56,
    "stack": []
  },
  "underflow": false
}