{
  "blocks": [
    {
      "ep": 15890493,
      "len": 9,
      "pred": [],
      "succ": [
        {
          "cond": true,
          "ep": 15890569
        },
        {
          "cond": false,
          "ep": 15890502
        }
      ]
    },
    {
      "ep": 15890569,
      "len": 9,
      "pred": [
        15890493
      ],
      "succ": [
        {
          "cond": false,
          "ep": 15890578
        }
      ]
    },
    {
      "ep": 15890578,
      "len": 66,
      "pred": [
        15890569,
        15890559,
        15890549,
        15890530,
        15890520
      ],
      "succ": [
        {
          "cond": true,
          "ep": 15890648
        },
        {
          "cond": false,
          "ep": 15890644
        }
      ]
    },
    {
      "ep": 15890648,
      "len": 11,
      "pred": [
        15890578,
        15890644
      ],
      "succ": []
    },
    {
      "ep": 15890644,
      "len": 4,
      "pred": [
        15890578
      ],
      "succ": [
        {
          "cond": false,
          "ep": 15890648
        }
      ]
    },
    {
      "ep": 15890502,
      "len": 9,
      "pred": [
        15890493
      ],
      "succ": [
        {
          "cond": true,
          "ep": 15890540
        },
        {
          "cond": false,
          "ep": 15890511
        }
      ]
    },
    {
      "ep": 15890540,
      "len": 9,
      "pred": [
        15890502
      ],
      "succ": [
        {
          "cond": true,
          "ep": 15890559
        },
        {
          "cond": false,
          "ep": 15890549
        }
      ]
    },
    {
      "ep": 15890559,
      "len": 10,
      "pred": [
        15890540
      ],
      "succ": [
        {
          "cond": true,
          "ep": 15890578
        }
      ]
    },
    {
      "ep": 15890549,
      "len": 10,
      "pred": [
        15890540
      ],
      "succ": [
        {
          "cond": true,
          "ep": 15890578
        }
      ]
    },
    {
      "ep": 15890511,
      "len": 9,
      "pred": [
        15890502
      ],
      "succ": [
        {
          "cond": true,
          "ep": 15890530
        },
        {
          "cond": false,
          "ep": 15890520
        }
      ]
    },
    {
      "ep": 15890530,
      "len": 10,
      "pred": [
        15890511
      ],
      "succ": [
        {
          "cond": true,
          "ep": 15890578
        }
      ]
    },
    {
      "ep": 15890520,
      "len": 10,
      "pred": [
        15890511
      ],
      "succ": [
        {
          "cond": true,
          "ep": 15890578
        }
      ]
    }
  ],
  "callees": [
    {
      "fun": 16063940,
      "loc": 15890578
    },
    {
      "fun": 15877515,
      "loc": 15890582
    },
    {
      "fun": 15877500,
      "loc": 15890586
    },
    {
      "fun": 16165944,
      "loc": 15890597
    },
    {
      "fun": 15877530,
      "loc": 15890616
    },
    {
      "fun": 15877515,
      "loc": 15890620
    }
  ],
  "callers": [
    {
      "fun": 15887215,
      "loc": 15887279
    },
    {
      "fun": 15888476,
      "loc": 15888807
    },
    {
      "fun": 15888120,
      "loc": 15888206
    }
  ],
  "start": 15890493,
  "state": {
    "clobbers": [
      {
        "ep": 14,
        "value": {
          "address": 4203461,
          "type": "Mem"
        }
      },
      {
        "ep": 14,
        "value": {
          "address": 4203464,
          "type": "Mem"
        }
      },
      {
        "ep": 14,
        "value": {
          "reg": 228,
          "size": 1,
          "type": "Reg"
        }
      },
      {
        "ep": 14,
        "value": {
          "address": 4203477,
          "type": "Mem"
        }
      },
      {
        "ep": 14,
        "value": {
          "address": 4203473,
          "type": "Mem"
        }
      },
      {
        "ep": 14,
        "value": {
          "address": 4203463,
          "type": "Mem"
        }
      },
      {
        "ep": 14,
        "value": {
          "address": 4203460,
          "type": "Mem"
        }
      },
      {
        "ep": 0,
        "value": {
          "reg": 224,
          "size": 0,
          "type": "Reg"
        }
      },
      {
        "ep": 14,
        "value": {
          "address": 4203479,
          "type": "Mem"
        }
      },
      {
        "ep": 14,
        "value": {
          "address": 4203475,
          "type": "Mem"
        }
      },
      {
        "ep": 37,
        "value": {
          "address": 4207338,
          "type": "Mem"
        }
      },
      {
        "ep": 14,
        "value": {
          "address": 4203472,
          "type": "Mem"
        }
      },
      {
        "ep": 14,
        "value": {
          "reg": 232,
          "size": 2,
          "type": "Reg"
        }
      },
      {
        "ep": 14,
        "value": {
          "address": 4203462,
          "type": "Mem"
        }
      },
      {
        "ep": 14,
        "value": {
          "reg": 236,
          "size": 2,
          "type": "Reg"
        }
      }
    ],
    "fun_stack": [],
    "input": [
      {
        "address": 4207329,
        "type": "Mem"
      },
      {
        "address": 4203463,
        "type": "Mem"
      },
      {
        "address": 4203464,
        "type": "Mem"
      },
      {
        "address": 4207346,
        "type": "Mem"
      },
      {
        "address": 4207317,
        "type": "Mem"
      },
      {
        "address": 4207320,
        "type": "Mem"
      }
    ],
    "output": [],
    "pc": 39,
    "stack": []
  },
  "underflow": false
}