{
  "blocks": [
    {
      "ep": 16772883,
      "len": 42,
      "pred": [],
      "succ": []
    }
  ],
  "callees": [],
  "callers": [
    {
      "fun": 16328464,
      "loc": 16232956
    },
    {
      "fun": 16772667,
      "loc": 16772674
    },
    {
      "fun": 16328464,
      "loc": 16322995
    },
    {
      "fun": 16752964,
      "loc": 16753102
    },
    {
      "fun": 16752964,
      "loc": 16753130
    },
    {
      "fun": 15949570,
      "loc": 15949678
    },
    {
      "fun": 15949570,
      "loc": 15949715
    },
    {
      "fun": 16231825,
      "loc": 16232956
    },
    {
      "fun": 16231825,
      "loc": 16322995
    },
    {
      "fun": 16328456,
      "loc": 16232956
    },
    {
      "fun": 16328456,
      "loc": 16322995
    },
    {
      "fun": 16232367,
      "loc": 16232956
    },
    {
      "fun": 16232367,
      "loc": 16322995
    },
    {
      "fun": 15858912,
      "loc": 15860454
    },
    {
      "fun": 15858912,
      "loc": 15860084
    },
    {
      "fun": 16752671,
      "loc": 16753102
    },
    {
      "fun": 16752671,
      "loc": 16753130
    }
  ],
  "start": 16772883,
  "state": {
    "clobbers": [
      {
        "ep": 16772888,
        "pc": 2,
        "value": {
          "address": 522,
          "type": "Mem"
        }
      },
      {
        "ep": 16772917,
        "pc": 7,
        "value": {
          "address": 4194308,
          "type": "Mem"
        }
      },
      {
        "ep": 16772910,
        "pc": 6,
        "value": {
          "address": 4194310,
          "type": "Mem"
        }
      },
      {
        "ep": 16772903,
        "pc": 5,
        "value": {
          "address": 4194312,
          "type": "Mem"
        }
      },
      {
        "ep": 16772893,
        "pc": 3,
        "value": {
          "address": 523,
          "type": "Mem"
        }
      },
      {
        "ep": 16772885,
        "pc": 1,
        "value": {
          "address": 153,
          "type": "Mem"
        }
      },
      {
        "ep": 16772897,
        "pc": 4,
        "value": {
          "address": 4194304,
          "type": "Mem"
        }
      }
    ],
    "fun_stack": [],
    "input": [],
    "output": [],
    "pc": 9,
    "stack": []
  },
  "underflow": false
}