{
  "blocks": [
    {
      "ep": 15953506,
      "len": 8,
      "pred": [],
      "succ": []
    }
  ],
  "callees": [],
  "callers": [
    {
      "fun": 16323904,
      "loc": 15979783
    },
    {
      "fun": 16328456,
      "loc": 15979783
    },
    {
      "fun": 16328464,
      "loc": 15979783
    },
    {
      "fun": 16231825,
      "loc": 15979783
    },
    {
      "fun": 16232367,
      "loc": 15979783
    }
  ],
  "start": 15953506,
  "state": {
    "clobbers": [],
    "fun_stack": [],
    "input": [],
    "output": [],
    "pc": 2,
    "stack": []
  },
  "underflow": false
}