{
  "state": {
    "clobbers": [
      {
        "ep": 0,
        "value": {
          "type": "Reg",
          "size": 0,
          "reg": 224
        }
      },
      {
        "ep": 3,
        "value": {
          "type": "Reg",
          "size": 2,
          "reg": 236
        }
      }
    ],
    "input": [
      {
        "type": "Reg",
        "size": 2,
        "reg": 236
      },
      {
        "type": "Reg",
        "size": 2,
        "reg": 232
      }
    ],
    "output": [],
    "fun_stack": [],
    "pc": 33
  },
  "start": 16041668,
  "blocks": [
    {
      "ep": 16041668,
      "pred": [],
      "succ": [],
      "insn": 33
    }
  ],
  "underflow": false,
  "callers": [
    {
      "loc": 16046983,
      "fun": 16046642
    },
    {
      "loc": 16047027,
      "fun": 16046642
    },
    {
      "loc": 16047071,
      "fun": 16046642
    },
    {
      "loc": 16047115,
      "fun": 16046642
    },
    {
      "loc": 16047159,
      "fun": 16046642
    },
    {
      "loc": 16047203,
      "fun": 16046642
    },
    {
      "loc": 16047247,
      "fun": 16046642
    },
    {
      "loc": 16047291,
      "fun": 16046642
    },
    {
      "loc": 16047335,
      "fun": 16046642
    },
    {
      "loc": 16044876,
      "fun": 16044514
    },
    {
      "loc": 16044920,
      "fun": 16044514
    },
    {
      "loc": 16044964,
      "fun": 16044514
    },
    {
      "loc": 16045008,
      "fun": 16044514
    },
    {
      "loc": 16045052,
      "fun": 16044514
    },
    {
      "loc": 16045096,
      "fun": 16044514
    },
    {
      "loc": 16045140,
      "fun": 16044514
    },
    {
      "loc": 16045184,
      "fun": 16044514
    },
    {
      "loc": 16045228,
      "fun": 16044514
    }
  ],
  "callees": []
}