{
  "state": {
    "clobbers": [],
    "input": [],
    "output": [],
    "stack": [],
    "fun_stack": [],
    "pc": 0
  },
  "start": 16048889,
  "blocks": [
    {
      "ep": 16048889,
      "pred": [],
      "succ": [
        {
          "ep": 16048898,
          "cond": false
        }
      ],
      "len": 9
    },
    {
      "ep": 16048898,
      "pred": [
        16048889,
        16048905
      ],
      "succ": [
        {
          "ep": 16048905,
          "cond": false
        }
      ],
      "len": 7
    },
    {
      "ep": 16048905,
      "pred": [
        16048898
      ],
      "succ": [
        {
          "ep": 16048898,
          "cond": true
        },
        {
          "ep": 16048910,
          "cond": false
        }
      ],
      "len": 5
    },
    {
      "ep": 16048910,
      "pred": [
        16048905
      ],
      "succ": [
        {
          "ep": 16048922,
          "cond": false
        }
      ],
      "len": 12
    },
    {
      "ep": 16048922,
      "pred": [
        16048910
      ],
      "succ": [
        {
          "ep": 16048934,
          "cond": false
        }
      ],
      "len": 12
    },
    {
      "ep": 16048934,
      "pred": [
        16048922
      ],
      "succ": [
        {
          "ep": 16048946,
          "cond": false
        }
      ],
      "len": 12
    },
    {
      "ep": 16048946,
      "pred": [
        16048934
      ],
      "succ": [
        {
          "ep": 16048962,
          "cond": false
        }
      ],
      "len": 16
    },
    {
      "ep": 16048962,
      "pred": [
        16048946
      ],
      "succ": [
        {
          "ep": 16048968,
          "cond": true
        },
        {
          "ep": 16048964,
          "cond": false
        }
      ],
      "len": 2
    },
    {
      "ep": 16048968,
      "pred": [
        16048962
      ],
      "succ": [
        {
          "ep": 16049014,
          "cond": false
        }
      ],
      "len": 46
    },
    {
      "ep": 16049014,
      "pred": [
        16048968
      ],
      "succ": [
        {
          "ep": 16049088,
          "cond": true
        },
        {
          "ep": 16049028,
          "cond": false
        }
      ],
      "len": 14
    },
    {
      "ep": 16049088,
      "pred": [
        16049014,
        16049028,
        16049038
      ],
      "succ": [
        {
          "ep": 16049089,
          "cond": false
        }
      ],
      "len": 1
    },
    {
      "ep": 16049089,
      "pred": [
        16049088,
        16049048
      ],
      "succ": [
        {
          "ep": 16049136,
          "cond": true
        }
      ],
      "len": 5
    },
    {
      "ep": 16049136,
      "pred": [
        16049089,
        16049072,
        16049066
      ],
      "succ": [
        {
          "ep": 16049151,
          "cond": true
        },
        {
          "ep": 16049141,
          "cond": false
        }
      ],
      "len": 5
    },
    {
      "ep": 16049151,
      "pred": [
        16049136
      ],
      "succ": [
        {
          "ep": 16049163,
          "cond": true
        },
        {
          "ep": 16049156,
          "cond": false
        }
      ],
      "len": 5
    },
    {
      "ep": 16049163,
      "pred": [
        16049151
      ],
      "succ": [],
      "len": 5
    },
    {
      "ep": 16049156,
      "pred": [
        16049151
      ],
      "succ": [],
      "len": 7
    },
    {
      "ep": 16049141,
      "pred": [
        16049136
      ],
      "succ": [
        {
          "ep": 16049150,
          "cond": true
        },
        {
          "ep": 16049146,
          "cond": false
        }
      ],
      "len": 5
    },
    {
      "ep": 16049150,
      "pred": [
        16049141,
        16049146
      ],
      "succ": [],
      "len": 1
    },
    {
      "ep": 16049146,
      "pred": [
        16049141
      ],
      "succ": [
        {
          "ep": 16049150,
          "cond": false
        }
      ],
      "len": 4
    },
    {
      "ep": 16049028,
      "pred": [
        16049014
      ],
      "succ": [
        {
          "ep": 16049088,
          "cond": true
        },
        {
          "ep": 16049038,
          "cond": false
        }
      ],
      "len": 10
    },
    {
      "ep": 16049038,
      "pred": [
        16049028
      ],
      "succ": [
        {
          "ep": 16049088,
          "cond": true
        },
        {
          "ep": 16049048,
          "cond": false
        }
      ],
      "len": 10
    },
    {
      "ep": 16049048,
      "pred": [
        16049038
      ],
      "succ": [
        {
          "ep": 16049089,
          "cond": true
        },
        {
          "ep": 16049056,
          "cond": false
        }
      ],
      "len": 8
    },
    {
      "ep": 16049056,
      "pred": [
        16049048
      ],
      "succ": [
        {
          "ep": 16049082,
          "cond": true
        },
        {
          "ep": 16049066,
          "cond": false
        }
      ],
      "len": 10
    },
    {
      "ep": 16049082,
      "pred": [
        16049056
      ],
      "succ": [
        {
          "ep": 16049072,
          "cond": true
        }
      ],
      "len": 6
    },
    {
      "ep": 16049072,
      "pred": [
        16049082,
        16049066
      ],
      "succ": [
        {
          "ep": 16049136,
          "cond": true
        }
      ],
      "len": 10
    },
    {
      "ep": 16049066,
      "pred": [
        16049056
      ],
      "succ": [
        {
          "ep": 16049136,
          "cond": true
        },
        {
          "ep": 16049072,
          "cond": false
        }
      ],
      "len": 6
    },
    {
      "ep": 16048964,
      "pred": [
        16048962
      ],
      "succ": [
        {
          "ep": 16049325,
          "cond": true
        }
      ],
      "len": 4
    },
    {
      "ep": 16049325,
      "pred": [
        16048964
      ],
      "succ": [
        {
          "ep": 16049374,
          "cond": false
        }
      ],
      "len": 49
    },
    {
      "ep": 16049374,
      "pred": [
        16049325
      ],
      "succ": [
        {
          "ep": 16049387,
          "cond": false
        }
      ],
      "len": 13
    },
    {
      "ep": 16049387,
      "pred": [
        16049374
      ],
      "succ": [
        {
          "ep": 16049495,
          "cond": true
        },
        {
          "ep": 16049410,
          "cond": false
        }
      ],
      "len": 23
    },
    {
      "ep": 16049495,
      "pred": [
        16049387,
        16049451,
        16049472,
        16049482
      ],
      "succ": [
        {
          "ep": 16049657,
          "cond": true
        },
        {
          "ep": 16049510,
          "cond": false
        }
      ],
      "len": 15
    },
    {
      "ep": 16049657,
      "pred": [
        16049495,
        16049531,
        16049562,
        16049568,
        16049591,
        16049643,
        16049461
      ],
      "succ": [],
      "len": 1
    },
    {
      "ep": 16049510,
      "pred": [
        16049495
      ],
      "succ": [
        {
          "ep": 16049531,
          "cond": false
        }
      ],
      "len": 21
    },
    {
      "ep": 16049531,
      "pred": [
        16049510
      ],
      "succ": [
        {
          "ep": 16049657,
          "cond": true
        },
        {
          "ep": 16049537,
          "cond": false
        }
      ],
      "len": 6
    },
    {
      "ep": 16049537,
      "pred": [
        16049531
      ],
      "succ": [
        {
          "ep": 16049562,
          "cond": false
        }
      ],
      "len": 25
    },
    {
      "ep": 16049562,
      "pred": [
        16049537
      ],
      "succ": [
        {
          "ep": 16049657,
          "cond": true
        },
        {
          "ep": 16049568,
          "cond": false
        }
      ],
      "len": 6
    },
    {
      "ep": 16049568,
      "pred": [
        16049562
      ],
      "succ": [
        {
          "ep": 16049657,
          "cond": true
        },
        {
          "ep": 16049578,
          "cond": false
        }
      ],
      "len": 10
    },
    {
      "ep": 16049578,
      "pred": [
        16049568
      ],
      "succ": [
        {
          "ep": 16049591,
          "cond": false
        }
      ],
      "len": 13
    },
    {
      "ep": 16049591,
      "pred": [
        16049578
      ],
      "succ": [
        {
          "ep": 16049657,
          "cond": true
        },
        {
          "ep": 16049614,
          "cond": false
        }
      ],
      "len": 23
    },
    {
      "ep": 16049614,
      "pred": [
        16049591
      ],
      "succ": [
        {
          "ep": 16049628,
          "cond": true
        },
        {
          "ep": 16049624,
          "cond": false
        }
      ],
      "len": 10
    },
    {
      "ep": 16049628,
      "pred": [
        16049614,
        16049624
      ],
      "succ": [
        {
          "ep": 16049643,
          "cond": false
        }
      ],
      "len": 15
    },
    {
      "ep": 16049643,
      "pred": [
        16049628
      ],
      "succ": [
        {
          "ep": 16049657,
          "cond": false
        }
      ],
      "len": 14
    },
    {
      "ep": 16049624,
      "pred": [
        16049614
      ],
      "succ": [
        {
          "ep": 16049628,
          "cond": false
        }
      ],
      "len": 4
    },
    {
      "ep": 16049410,
      "pred": [
        16049387
      ],
      "succ": [
        {
          "ep": 16049442,
          "cond": true
        },
        {
          "ep": 16049424,
          "cond": false
        }
      ],
      "len": 14
    },
    {
      "ep": 16049442,
      "pred": [
        16049410,
        16049433
      ],
      "succ": [
        {
          "ep": 16049451,
          "cond": false
        }
      ],
      "len": 9
    },
    {
      "ep": 16049451,
      "pred": [
        16049442
      ],
      "succ": [
        {
          "ep": 16049495,
          "cond": true
        },
        {
          "ep": 16049461,
          "cond": false
        }
      ],
      "len": 10
    },
    {
      "ep": 16049461,
      "pred": [
        16049451
      ],
      "succ": [
        {
          "ep": 16049657,
          "cond": true
        },
        {
          "ep": 16049472,
          "cond": false
        }
      ],
      "len": 11
    },
    {
      "ep": 16049472,
      "pred": [
        16049461
      ],
      "succ": [
        {
          "ep": 16049495,
          "cond": true
        },
        {
          "ep": 16049482,
          "cond": false
        }
      ],
      "len": 10
    },
    {
      "ep": 16049482,
      "pred": [
        16049472
      ],
      "succ": [
        {
          "ep": 16049495,
          "cond": false
        }
      ],
      "len": 13
    },
    {
      "ep": 16049424,
      "pred": [
        16049410
      ],
      "succ": [
        {
          "ep": 16049433,
          "cond": false
        }
      ],
      "len": 9
    },
    {
      "ep": 16049433,
      "pred": [
        16049424
      ],
      "succ": [
        {
          "ep": 16049442,
          "cond": false
        }
      ],
      "len": 9
    }
  ],
  "underflow": true,
  "callers": [
    {
      "loc": 16150263,
      "fun": 16147061
    }
  ],
  "callees": [
    {
      "loc": 16049325,
      "fun": 16061451
    },
    {
      "loc": 16049346,
      "fun": 16061882
    },
    {
      "loc": 16049350,
      "fun": 16060636
    },
    {
      "loc": 16049410,
      "fun": 16061124
    },
    {
      "loc": 16049424,
      "fun": 16040688
    },
    {
      "loc": 16049433,
      "fun": 16052672
    },
    {
      "loc": 16049442,
      "fun": 16049901
    },
    {
      "loc": 16049461,
      "fun": 16062042
    },
    {
      "loc": 16049465,
      "fun": 16049901
    },
    {
      "loc": 16049495,
      "fun": 16061124
    },
    {
      "loc": 16049499,
      "fun": 16061882
    },
    {
      "loc": 16049503,
      "fun": 16048335
    },
    {
      "loc": 16049510,
      "fun": 16060758
    },
    {
      "loc": 16049514,
      "fun": 16062042
    },
    {
      "loc": 16049531,
      "fun": 16040692
    },
    {
      "loc": 16049537,
      "fun": 16060575
    },
    {
      "loc": 16049541,
      "fun": 16060758
    },
    {
      "loc": 16049545,
      "fun": 16062042
    },
    {
      "loc": 16049562,
      "fun": 16040692
    },
    {
      "loc": 16049568,
      "fun": 16060575
    },
    {
      "loc": 16049572,
      "fun": 16039015
    },
    {
      "loc": 16049604,
      "fun": 16061401
    },
    {
      "loc": 16049608,
      "fun": 16046431
    },
    {
      "loc": 16049624,
      "fun": 16061401
    },
    {
      "loc": 16049653,
      "fun": 16052962
    },
    {
      "loc": 16048997,
      "fun": 16060880
    },
    {
      "loc": 16049001,
      "fun": 16059613
    },
    {
      "loc": 16049005,
      "fun": 16040018
    },
    {
      "loc": 16049014,
      "fun": 16060758
    },
    {
      "loc": 16049018,
      "fun": 16060819
    },
    {
      "loc": 16049022,
      "fun": 16040018
    },
    {
      "loc": 16049028,
      "fun": 16060819
    },
    {
      "loc": 16049032,
      "fun": 16040018
    },
    {
      "loc": 16049038,
      "fun": 16060575
    },
    {
      "loc": 16049042,
      "fun": 16040018
    },
    {
      "loc": 16049050,
      "fun": 16049168
    },
    {
      "loc": 16049056,
      "fun": 16061882
    }
  ]
}