{
  "state": {
    "clobbers": [
      {
        "ep": 16,
        "value": {
          "type": "Mem",
          "address": 9877
        }
      },
      {
        "ep": 22,
        "value": {
          "type": "Reg",
          "size": 2,
          "reg": 224
        }
      },
      {
        "ep": 17,
        "value": {
          "type": "Mem",
          "address": 9857
        }
      },
      {
        "ep": 19,
        "value": {
          "type": "Mem",
          "address": 9192
        }
      },
      {
        "ep": 19,
        "value": {
          "type": "Reg",
          "size": 2,
          "reg": 232
        }
      },
      {
        "ep": 17,
        "value": {
          "type": "Mem",
          "address": 9158
        }
      },
      {
        "ep": 17,
        "value": {
          "type": "Mem",
          "address": 9164
        }
      },
      {
        "ep": 15,
        "value": {
          "type": "Mem",
          "address": 9871
        }
      },
      {
        "ep": 19,
        "value": {
          "type": "Reg",
          "size": 2,
          "reg": 228
        }
      },
      {
        "ep": 13,
        "value": {
          "type": "Mem",
          "address": 9883
        }
      },
      {
        "ep": 6,
        "value": {
          "type": "Mem",
          "address": 9865
        }
      },
      {
        "ep": 16,
        "value": {
          "type": "Mem",
          "address": 9885
        }
      },
      {
        "ep": 19,
        "value": {
          "type": "Mem",
          "address": 9188
        }
      },
      {
        "ep": 19,
        "value": {
          "type": "Mem",
          "address": 9194
        }
      },
      {
        "ep": 17,
        "value": {
          "type": "Mem",
          "address": 9162
        }
      },
      {
        "ep": 17,
        "value": {
          "type": "Mem",
          "address": 9157
        }
      },
      {
        "ep": 17,
        "value": {
          "type": "Mem",
          "address": 9160
        }
      },
      {
        "ep": 17,
        "value": {
          "type": "Mem",
          "address": 9166
        }
      },
      {
        "ep": 6,
        "value": {
          "type": "Reg",
          "size": 2,
          "reg": 236
        }
      },
      {
        "ep": 16,
        "value": {
          "type": "Mem",
          "address": 9887
        }
      },
      {
        "ep": 19,
        "value": {
          "type": "Mem",
          "address": 9190
        }
      },
      {
        "ep": 19,
        "value": {
          "type": "Mem",
          "address": 9196
        }
      },
      {
        "ep": 19,
        "value": {
          "type": "Mem",
          "address": 9873
        }
      }
    ],
    "input": [
      {
        "type": "Mem",
        "address": 9857
      },
      {
        "type": "Mem",
        "address": 11910
      },
      {
        "type": "Mem",
        "address": 9865
      },
      {
        "type": "Mem",
        "address": 9873
      },
      {
        "type": "Mem",
        "address": 9875
      },
      {
        "type": "Mem",
        "address": 9881
      },
      {
        "type": "Mem",
        "address": 9883
      },
      {
        "type": "Mem",
        "address": 9917
      },
      {
        "type": "Mem",
        "address": 9922
      },
      {
        "type": "Mem",
        "address": 9156
      },
      {
        "type": "Mem",
        "address": 9157
      },
      {
        "type": "Mem",
        "address": 9158
      },
      {
        "type": "Mem",
        "address": 9159
      },
      {
        "type": "Mem",
        "address": 9160
      },
      {
        "type": "Mem",
        "address": 9161
      },
      {
        "type": "Mem",
        "address": 9170
      },
      {
        "type": "Mem",
        "address": 9188
      },
      {
        "type": "Mem",
        "address": 9190
      },
      {
        "type": "Mem",
        "address": 9192
      },
      {
        "type": "Mem",
        "address": 9194
      },
      {
        "type": "Mem",
        "address": 9196
      }
    ],
    "output": [],
    "stack": [],
    "fun_stack": [],
    "pc": 27
  },
  "start": 16165967,
  "blocks": [
    {
      "ep": 16165967,
      "pred": [],
      "succ": [
        {
          "ep": 16165990,
          "cond": true
        },
        {
          "ep": 16165977,
          "cond": false
        }
      ],
      "len": 10
    },
    {
      "ep": 16165990,
      "pred": [
        16165967,
        16165977
      ],
      "succ": [
        {
          "ep": 16166058,
          "cond": true
        },
        {
          "ep": 16166007,
          "cond": false
        }
      ],
      "len": 17
    },
    {
      "ep": 16166058,
      "pred": [
        16165990
      ],
      "succ": [
        {
          "ep": 16166206,
          "cond": true
        },
        {
          "ep": 16166069,
          "cond": false
        }
      ],
      "len": 11
    },
    {
      "ep": 16166206,
      "pred": [
        16166058
      ],
      "succ": [
        {
          "ep": 16166250,
          "cond": true
        },
        {
          "ep": 16166216,
          "cond": false
        }
      ],
      "len": 10
    },
    {
      "ep": 16166250,
      "pred": [
        16166206
      ],
      "succ": [
        {
          "ep": 16166329,
          "cond": true
        },
        {
          "ep": 16166259,
          "cond": false
        }
      ],
      "len": 9
    },
    {
      "ep": 16166329,
      "pred": [
        16166250
      ],
      "succ": [
        {
          "ep": 16166365,
          "cond": true
        },
        {
          "ep": 16166339,
          "cond": false
        }
      ],
      "len": 10
    },
    {
      "ep": 16166365,
      "pred": [
        16166329
      ],
      "succ": [
        {
          "ep": 16166321,
          "cond": true
        }
      ],
      "len": 16
    },
    {
      "ep": 16166321,
      "pred": [
        16166365,
        16166359,
        16166279,
        16166317
      ],
      "succ": [
        {
          "ep": 16166041,
          "cond": true
        }
      ],
      "len": 8
    },
    {
      "ep": 16166041,
      "pred": [
        16166321,
        16166037,
        16166131
      ],
      "succ": [
        {
          "ep": 16166057,
          "cond": false
        }
      ],
      "len": 16
    },
    {
      "ep": 16166057,
      "pred": [
        16166041,
        16166216,
        16166020,
        16166137,
        16166162,
        16166106,
        16166085
      ],
      "succ": [],
      "len": 1
    },
    {
      "ep": 16166339,
      "pred": [
        16166329
      ],
      "succ": [
        {
          "ep": 16166359,
          "cond": false
        }
      ],
      "len": 20
    },
    {
      "ep": 16166359,
      "pred": [
        16166339
      ],
      "succ": [
        {
          "ep": 16166321,
          "cond": true
        }
      ],
      "len": 6
    },
    {
      "ep": 16166259,
      "pred": [
        16166250
      ],
      "succ": [
        {
          "ep": 16166279,
          "cond": false
        }
      ],
      "len": 20
    },
    {
      "ep": 16166279,
      "pred": [
        16166259
      ],
      "succ": [
        {
          "ep": 16166321,
          "cond": true
        },
        {
          "ep": 16166297,
          "cond": false
        }
      ],
      "len": 18
    },
    {
      "ep": 16166297,
      "pred": [
        16166279
      ],
      "succ": [
        {
          "ep": 16166317,
          "cond": false
        }
      ],
      "len": 20
    },
    {
      "ep": 16166317,
      "pred": [
        16166297
      ],
      "succ": [
        {
          "ep": 16166321,
          "cond": false
        }
      ],
      "len": 4
    },
    {
      "ep": 16166216,
      "pred": [
        16166206
      ],
      "succ": [
        {
          "ep": 16166057,
          "cond": true
        },
        {
          "ep": 16166234,
          "cond": false
        }
      ],
      "len": 18
    },
    {
      "ep": 16166234,
      "pred": [
        16166216
      ],
      "succ": [
        {
          "ep": 16166020,
          "cond": true
        }
      ],
      "len": 16
    },
    {
      "ep": 16166020,
      "pred": [
        16166234,
        16166007
      ],
      "succ": [
        {
          "ep": 16166057,
          "cond": true
        },
        {
          "ep": 16166037,
          "cond": false
        }
      ],
      "len": 17
    },
    {
      "ep": 16166037,
      "pred": [
        16166020
      ],
      "succ": [
        {
          "ep": 16166041,
          "cond": false
        }
      ],
      "len": 4
    },
    {
      "ep": 16166069,
      "pred": [
        16166058
      ],
      "succ": [
        {
          "ep": 16166137,
          "cond": true
        },
        {
          "ep": 16166085,
          "cond": false
        }
      ],
      "len": 16
    },
    {
      "ep": 16166137,
      "pred": [
        16166069
      ],
      "succ": [
        {
          "ep": 16166057,
          "cond": true
        },
        {
          "ep": 16166162,
          "cond": false
        }
      ],
      "len": 25
    },
    {
      "ep": 16166162,
      "pred": [
        16166137
      ],
      "succ": [
        {
          "ep": 16166057,
          "cond": true
        },
        {
          "ep": 16166196,
          "cond": false
        }
      ],
      "len": 34
    },
    {
      "ep": 16166196,
      "pred": [
        16166162
      ],
      "succ": [
        {
          "ep": 16166106,
          "cond": true
        }
      ],
      "len": 10
    },
    {
      "ep": 16166106,
      "pred": [
        16166196,
        16166102
      ],
      "succ": [
        {
          "ep": 16166057,
          "cond": true
        },
        {
          "ep": 16166131,
          "cond": false
        }
      ],
      "len": 25
    },
    {
      "ep": 16166131,
      "pred": [
        16166106
      ],
      "succ": [
        {
          "ep": 16166041,
          "cond": true
        }
      ],
      "len": 6
    },
    {
      "ep": 16166085,
      "pred": [
        16166069
      ],
      "succ": [
        {
          "ep": 16166057,
          "cond": true
        },
        {
          "ep": 16166102,
          "cond": false
        }
      ],
      "len": 17
    },
    {
      "ep": 16166102,
      "pred": [
        16166085
      ],
      "succ": [
        {
          "ep": 16166106,
          "cond": false
        }
      ],
      "len": 4
    },
    {
      "ep": 16166007,
      "pred": [
        16165990
      ],
      "succ": [
        {
          "ep": 16166020,
          "cond": false
        }
      ],
      "len": 13
    },
    {
      "ep": 16165977,
      "pred": [
        16165967
      ],
      "succ": [
        {
          "ep": 16165990,
          "cond": false
        }
      ],
      "len": 13
    }
  ],
  "underflow": false,
  "callers": [
    {
      "loc": 16343093,
      "fun": 16343067
    }
  ],
  "callees": [
    {
      "loc": 16165990,
      "fun": 16169157
    },
    {
      "loc": 16165994,
      "fun": 16169215
    },
    {
      "loc": 16166027,
      "fun": 16169813
    },
    {
      "loc": 16166031,
      "fun": 16166398
    },
    {
      "loc": 16166037,
      "fun": 16168027
    },
    {
      "loc": 16166041,
      "fun": 16169211
    },
    {
      "loc": 16166045,
      "fun": 16169328
    },
    {
      "loc": 16166092,
      "fun": 16169813
    },
    {
      "loc": 16166096,
      "fun": 16166398
    },
    {
      "loc": 16166102,
      "fun": 16168027
    },
    {
      "loc": 16166106,
      "fun": 16169262
    },
    {
      "loc": 16166110,
      "fun": 16059967
    },
    {
      "loc": 16166121,
      "fun": 16169813
    },
    {
      "loc": 16166125,
      "fun": 16166398
    },
    {
      "loc": 16166131,
      "fun": 16168020
    },
    {
      "loc": 16166137,
      "fun": 16061882
    },
    {
      "loc": 16166141,
      "fun": 16060880
    },
    {
      "loc": 16166152,
      "fun": 16169813
    },
    {
      "loc": 16166156,
      "fun": 16166398
    },
    {
      "loc": 16166162,
      "fun": 16168027
    },
    {
      "loc": 16166166,
      "fun": 16170543
    },
    {
      "loc": 16166170,
      "fun": 16170589
    },
    {
      "loc": 16166174,
      "fun": 16061882
    },
    {
      "loc": 16166185,
      "fun": 16169813
    },
    {
      "loc": 16166189,
      "fun": 16166398
    },
    {
      "loc": 16166196,
      "fun": 16168020
    },
    {
      "loc": 16166200,
      "fun": 16170619
    },
    {
      "loc": 16166223,
      "fun": 16169813
    },
    {
      "loc": 16166227,
      "fun": 16166398
    },
    {
      "loc": 16166234,
      "fun": 16168027
    },
    {
      "loc": 16166238,
      "fun": 16169320
    },
    {
      "loc": 16166242,
      "fun": 16059967
    },
    {
      "loc": 16166266,
      "fun": 16169813
    },
    {
      "loc": 16166270,
      "fun": 16166398
    },
    {
      "loc": 16166279,
      "fun": 16168027
    },
    {
      "loc": 16166283,
      "fun": 16059967
    },
    {
      "loc": 16166287,
      "fun": 16169338
    },
    {
      "loc": 16166291,
      "fun": 16169384
    },
    {
      "loc": 16166304,
      "fun": 16169813
    },
    {
      "loc": 16166308,
      "fun": 16166398
    },
    {
      "loc": 16166317,
      "fun": 16168020
    },
    {
      "loc": 16166321,
      "fun": 16169324
    },
    {
      "loc": 16166329,
      "fun": 16059967
    },
    {
      "loc": 16166333,
      "fun": 16169384
    },
    {
      "loc": 16166346,
      "fun": 16169813
    },
    {
      "loc": 16166350,
      "fun": 16166398
    },
    {
      "loc": 16166359,
      "fun": 16168027
    },
    {
      "loc": 16166370,
      "fun": 16168145
    }
  ]
}