{
  "state": {
    "clobbers": [
      {
        "ep": 15,
        "value": {
          "type": "Mem",
          "address": 11779
        }
      },
      {
        "ep": 3,
        "value": {
          "type": "Mem",
          "address": 7320
        }
      },
      {
        "ep": 58,
        "value": {
          "type": "Mem",
          "address": 11768
        }
      },
      {
        "ep": 3,
        "value": {
          "type": "Mem",
          "address": 11771
        }
      },
      {
        "ep": 54,
        "value": {
          "type": "Mem",
          "address": 11902
        }
      },
      {
        "ep": 56,
        "value": {
          "type": "Mem",
          "address": 11792
        }
      },
      {
        "ep": 56,
        "value": {
          "type": "Mem",
          "address": 11789
        }
      },
      {
        "ep": 3,
        "value": {
          "type": "Reg",
          "size": 2,
          "reg": 236
        }
      },
      {
        "ep": 15,
        "value": {
          "type": "Reg",
          "size": 2,
          "reg": 224
        }
      },
      {
        "ep": 3,
        "value": {
          "type": "Mem",
          "address": 7319
        }
      },
      {
        "ep": 3,
        "value": {
          "type": "Mem",
          "address": 7322
        }
      },
      {
        "ep": 3,
        "value": {
          "type": "Reg",
          "size": 2,
          "reg": 252
        }
      },
      {
        "ep": 3,
        "value": {
          "type": "Reg",
          "size": 2,
          "reg": 232
        }
      },
      {
        "ep": 2,
        "value": {
          "type": "Mem",
          "address": 11759
        }
      },
      {
        "ep": 3,
        "value": {
          "type": "Reg",
          "size": 2,
          "reg": 228
        }
      },
      {
        "ep": 3,
        "value": {
          "type": "Mem",
          "address": 7321
        }
      },
      {
        "ep": 3,
        "value": {
          "type": "Mem",
          "address": 7037
        }
      },
      {
        "ep": 3,
        "value": {
          "type": "Mem",
          "address": 11775
        }
      },
      {
        "ep": 56,
        "value": {
          "type": "Mem",
          "address": 11790
        }
      },
      {
        "ep": 3,
        "value": {
          "type": "Mem",
          "address": 7302
        }
      }
    ],
    "input": [
      {
        "type": "Mem",
        "address": 11904
      },
      {
        "type": "Mem",
        "address": 11905
      },
      {
        "type": "Reg",
        "size": 2,
        "reg": 252
      },
      {
        "type": "Mem",
        "address": 11906
      },
      {
        "type": "Mem",
        "address": 11781
      },
      {
        "type": "Mem",
        "address": 11784
      },
      {
        "type": "Mem",
        "address": 11759
      },
      {
        "type": "Mem",
        "address": 7316
      },
      {
        "type": "Mem",
        "address": 11899
      },
      {
        "type": "Mem",
        "address": 11901
      },
      {
        "type": "Mem",
        "address": 11903
      }
    ],
    "output": [],
    "stack": [],
    "fun_stack": [],
    "pc": 72
  },
  "start": 16218150,
  "blocks": [
    {
      "ep": 16218150,
      "pred": [],
      "succ": [
        {
          "ep": 16218192,
          "cond": true
        },
        {
          "ep": 16218183,
          "cond": false
        }
      ],
      "len": 33
    },
    {
      "ep": 16218192,
      "pred": [
        16218150,
        16218183
      ],
      "succ": [
        {
          "ep": 16218205,
          "cond": false
        }
      ],
      "len": 13
    },
    {
      "ep": 16218205,
      "pred": [
        16218192,
        16218183
      ],
      "succ": [
        {
          "ep": 16218255,
          "cond": true
        },
        {
          "ep": 16218226,
          "cond": false
        }
      ],
      "len": 21
    },
    {
      "ep": 16218255,
      "pred": [
        16218205,
        16218226
      ],
      "succ": [
        {
          "ep": 16218262,
          "cond": true
        },
        {
          "ep": 16218260,
          "cond": false
        }
      ],
      "len": 5
    },
    {
      "ep": 16218262,
      "pred": [
        16218255,
        16218260
      ],
      "succ": [
        {
          "ep": 16218300,
          "cond": true
        },
        {
          "ep": 16218292,
          "cond": false
        }
      ],
      "len": 30
    },
    {
      "ep": 16218300,
      "pred": [
        16218262,
        16218292
      ],
      "succ": [
        {
          "ep": 16218336,
          "cond": true
        },
        {
          "ep": 16218311,
          "cond": false
        }
      ],
      "len": 11
    },
    {
      "ep": 16218336,
      "pred": [
        16218300
      ],
      "succ": [
        {
          "ep": 16218342,
          "cond": false
        }
      ],
      "len": 6
    },
    {
      "ep": 16218342,
      "pred": [
        16218336,
        16218311,
        16218330,
        16218325
      ],
      "succ": [
        {
          "ep": 16218371,
          "cond": true
        },
        {
          "ep": 16218369,
          "cond": false
        }
      ],
      "len": 27
    },
    {
      "ep": 16218371,
      "pred": [
        16218342,
        16218369
      ],
      "succ": [
        {
          "ep": 16218391,
          "cond": true
        },
        {
          "ep": 16218380,
          "cond": false
        }
      ],
      "len": 9
    },
    {
      "ep": 16218391,
      "pred": [
        16218371,
        16218380,
        16218369
      ],
      "succ": [],
      "len": 1
    },
    {
      "ep": 16218380,
      "pred": [
        16218371
      ],
      "succ": [
        {
          "ep": 16218391,
          "cond": false
        }
      ],
      "len": 11
    },
    {
      "ep": 16218369,
      "pred": [
        16218342
      ],
      "succ": [
        {
          "ep": 16218391,
          "cond": true
        },
        {
          "ep": 16218371,
          "cond": false
        }
      ],
      "len": 2
    },
    {
      "ep": 16218311,
      "pred": [
        16218300
      ],
      "succ": [
        {
          "ep": 16218342,
          "cond": true
        },
        {
          "ep": 16218316,
          "cond": false
        }
      ],
      "len": 5
    },
    {
      "ep": 16218316,
      "pred": [
        16218311
      ],
      "succ": [
        {
          "ep": 16218330,
          "cond": true
        },
        {
          "ep": 16218325,
          "cond": false
        }
      ],
      "len": 9
    },
    {
      "ep": 16218330,
      "pred": [
        16218316,
        16218325
      ],
      "succ": [
        {
          "ep": 16218342,
          "cond": true
        }
      ],
      "len": 6
    },
    {
      "ep": 16218325,
      "pred": [
        16218316
      ],
      "succ": [
        {
          "ep": 16218342,
          "cond": true
        },
        {
          "ep": 16218330,
          "cond": false
        }
      ],
      "len": 5
    },
    {
      "ep": 16218292,
      "pred": [
        16218262
      ],
      "succ": [
        {
          "ep": 16218300,
          "cond": false
        }
      ],
      "len": 8
    },
    {
      "ep": 16218260,
      "pred": [
        16218255
      ],
      "succ": [
        {
          "ep": 16218262,
          "cond": false
        }
      ],
      "len": 2
    },
    {
      "ep": 16218226,
      "pred": [
        16218205
      ],
      "succ": [
        {
          "ep": 16218255,
          "cond": false
        }
      ],
      "len": 29
    },
    {
      "ep": 16218183,
      "pred": [
        16218150
      ],
      "succ": [
        {
          "ep": 16218205,
          "cond": true
        },
        {
          "ep": 16218192,
          "cond": false
        }
      ],
      "len": 9
    }
  ],
  "underflow": false,
  "callers": [
    {
      "loc": 16218045,
      "fun": 16217818
    }
  ],
  "callees": [
    {
      "loc": 16218163,
      "fun": 16218661
    },
    {
      "loc": 16218205,
      "fun": 16221592
    },
    {
      "loc": 16218267,
      "fun": 16227662
    },
    {
      "loc": 16218278,
      "fun": 16220626
    },
    {
      "loc": 16218330,
      "fun": 16224914
    },
    {
      "loc": 16218342,
      "fun": 16220075
    },
    {
      "loc": 16218382,
      "fun": 16220224
    },
    {
      "loc": 16218338,
      "fun": 16224817
    }
  ]
}