{
  "blocks": [
    {
      "ep": 16287678,
      "len": 14,
      "pred": [],
      "succ": [
        {
          "cond": false,
          "ep": 16287692
        }
      ]
    },
    {
      "ep": 16287692,
      "len": 20,
      "pred": [
        16287678
      ],
      "succ": [
        {
          "cond": false,
          "ep": 16287712
        }
      ]
    },
    {
      "ep": 16287712,
      "len": 4,
      "pred": [
        16287692
      ],
      "succ": [
        {
          "cond": false,
          "ep": 16287716
        }
      ]
    },
    {
      "ep": 16287716,
      "len": 10,
      "pred": [
        16287712,
        16287734
      ],
      "succ": [
        {
          "cond": false,
          "ep": 16287726
        }
      ]
    },
    {
      "ep": 16287726,
      "len": 8,
      "pred": [
        16287716
      ],
      "succ": [
        {
          "cond": false,
          "ep": 16287734
        }
      ]
    },
    {
      "ep": 16287734,
      "len": 5,
      "pred": [
        16287726
      ],
      "succ": [
        {
          "cond": true,
          "ep": 16287716
        },
        {
          "cond": false,
          "ep": 16287739
        }
      ]
    },
    {
      "ep": 16287739,
      "len": 20,
      "pred": [
        16287734
      ],
      "succ": [
        {
          "cond": true,
          "ep": 16287774
        },
        {
          "cond": false,
          "ep": 16287759
        }
      ]
    },
    {
      "ep": 16287774,
      "len": 14,
      "pred": [
        16287739,
        16287764
      ],
      "succ": [
        {
          "cond": false,
          "ep": 16287788
        }
      ]
    },
    {
      "ep": 16287788,
      "len": 14,
      "pred": [
        16287774
      ],
      "succ": [
        {
          "cond": true,
          "ep": 16287898
        },
        {
          "cond": false,
          "ep": 16287802
        }
      ]
    },
    {
      "ep": 16287898,
      "len": 20,
      "pred": [
        16287788,
        16287816,
        16287897,
        16287881,
        16287804
      ],
      "succ": [
        {
          "cond": true,
          "ep": 16287891
        }
      ]
    },
    {
      "ep": 16287891,
      "len": 6,
      "pred": [
        16287898,
        16287886
      ],
      "succ": []
    },
    {
      "ep": 16287802,
      "len": 2,
      "pred": [
        16287788
      ],
      "succ": [
        {
          "cond": true,
          "ep": 16287816
        },
        {
          "cond": false,
          "ep": 16287804
        }
      ]
    },
    {
      "ep": 16287816,
      "len": 13,
      "pred": [
        16287802,
        16287813
      ],
      "succ": [
        {
          "cond": true,
          "ep": 16287898
        },
        {
          "cond": false,
          "ep": 16287829
        }
      ]
    },
    {
      "ep": 16287829,
      "len": 22,
      "pred": [
        16287816
      ],
      "succ": [
        {
          "cond": false,
          "ep": 16287851
        }
      ]
    },
    {
      "ep": 16287851,
      "len": 12,
      "pred": [
        16287829,
        16287875
      ],
      "succ": [
        {
          "cond": true,
          "ep": 16287897
        },
        {
          "cond": false,
          "ep": 16287863
        }
      ]
    },
    {
      "ep": 16287897,
      "len": 1,
      "pred": [
        16287851
      ],
      "succ": [
        {
          "cond": false,
          "ep": 16287898
        }
      ]
    },
    {
      "ep": 16287863,
      "len": 12,
      "pred": [
        16287851
      ],
      "succ": [
        {
          "cond": true,
          "ep": 16287881
        },
        {
          "cond": false,
          "ep": 16287875
        }
      ]
    },
    {
      "ep": 16287881,
      "len": 5,
      "pred": [
        16287863
      ],
      "succ": [
        {
          "cond": true,
          "ep": 16287898
        },
        {
          "cond": false,
          "ep": 16287886
        }
      ]
    },
    {
      "ep": 16287886,
      "len": 5,
      "pred": [
        16287881
      ],
      "succ": [
        {
          "cond": false,
          "ep": 16287891
        }
      ]
    },
    {
      "ep": 16287875,
      "len": 6,
      "pred": [
        16287863
      ],
      "succ": [
        {
          "cond": true,
          "ep": 16287851
        }
      ]
    },
    {
      "ep": 16287804,
      "len": 9,
      "pred": [
        16287802
      ],
      "succ": [
        {
          "cond": true,
          "ep": 16287898
        },
        {
          "cond": false,
          "ep": 16287813
        }
      ]
    },
    {
      "ep": 16287813,
      "len": 3,
      "pred": [
        16287804
      ],
      "succ": [
        {
          "cond": false,
          "ep": 16287816
        }
      ]
    },
    {
      "ep": 16287759,
      "len": 5,
      "pred": [
        16287739
      ],
      "succ": [
        {
          "cond": false,
          "ep": 16287764
        }
      ]
    },
    {
      "ep": 16287764,
      "len": 10,
      "pred": [
        16287759
      ],
      "succ": [
        {
          "cond": false,
          "ep": 16287774
        }
      ]
    }
  ],
  "callees": [
    {
      "fun": 16286875,
      "loc": 16287683
    }
  ],
  "callers": [
    {
      "fun": 16753459,
      "loc": 15978862
    },
    {
      "fun": 16753459,
      "loc": 15978876
    },
    {
      "fun": 16753459,
      "loc": 15978887
    },
    {
      "fun": 16753459,
      "loc": 15978898
    },
    {
      "fun": 16753459,
      "loc": 15978909
    },
    {
      "fun": 16753459,
      "loc": 15978920
    },
    {
      "fun": 16753459,
      "loc": 15978931
    },
    {
      "fun": 16753459,
      "loc": 15978942
    },
    {
      "fun": 16753459,
      "loc": 15978953
    },
    {
      "fun": 16753275,
      "loc": 15978862
    },
    {
      "fun": 16753275,
      "loc": 15978876
    },
    {
      "fun": 16753275,
      "loc": 15978887
    },
    {
      "fun": 16753275,
      "loc": 15978898
    },
    {
      "fun": 16753275,
      "loc": 15978909
    },
    {
      "fun": 16753275,
      "loc": 15978920
    },
    {
      "fun": 16753275,
      "loc": 15978931
    },
    {
      "fun": 16753275,
      "loc": 15978942
    },
    {
      "fun": 16753275,
      "loc": 15978953
    },
    {
      "fun": 16323258,
      "loc": 15978862
    },
    {
      "fun": 16323258,
      "loc": 15978876
    },
    {
      "fun": 16323258,
      "loc": 15978887
    },
    {
      "fun": 16323258,
      "loc": 15978898
    },
    {
      "fun": 16323258,
      "loc": 15978909
    },
    {
      "fun": 16323258,
      "loc": 15978920
    },
    {
      "fun": 16323258,
      "loc": 15978931
    },
    {
      "fun": 16323258,
      "loc": 15978942
    },
    {
      "fun": 16323258,
      "loc": 15978953
    },
    {
      "fun": 16752640,
      "loc": 15978862
    },
    {
      "fun": 16752640,
      "loc": 15978876
    },
    {
      "fun": 16752640,
      "loc": 15978887
    },
    {
      "fun": 16752640,
      "loc": 15978898
    },
    {
      "fun": 16752640,
      "loc": 15978909
    },
    {
      "fun": 16752640,
      "loc": 15978920
    },
    {
      "fun": 16752640,
      "loc": 15978931
    },
    {
      "fun": 16752640,
      "loc": 15978942
    },
    {
      "fun": 16752640,
      "loc": 15978953
    },
    {
      "fun": 15866758,
      "loc": 15978862
    },
    {
      "fun": 15866758,
      "loc": 15978876
    },
    {
      "fun": 15866758,
      "loc": 15978887
    },
    {
      "fun": 15866758,
      "loc": 15978898
    },
    {
      "fun": 15866758,
      "loc": 15978909
    },
    {
      "fun": 15866758,
      "loc": 15978920
    },
    {
      "fun": 15866758,
      "loc": 15978931
    },
    {
      "fun": 15866758,
      "loc": 15978942
    },
    {
      "fun": 15866758,
      "loc": 15978953
    }
  ],
  "start": 16287678,
  "state": {
    "clobbers": [
      {
        "ep": 5,
        "value": {
          "reg": 224,
          "size": 0,
          "type": "Reg"
        }
      },
      {
        "ep": 5,
        "value": {
          "address": 7393,
          "type": "Mem"
        }
      }
    ],
    "fun_stack": [],
    "input": [
      {
        "address": 7385,
        "type": "Mem"
      },
      {
        "reg": 236,
        "size": 2,
        "type": "Reg"
      }
    ],
    "output": [],
    "pc": 2,
    "stack": []
  },
  "underflow": false
}